{
    "$schema": "https://biomejs.dev/schemas/1.4.1/schema.json",
    "organizeImports": {
      "enabled": true
    },
    "linter": {
      "enabled": true,
      "rules": {
        "recommended": true,
        "complexity": {
          "noExtraBooleanCast": "error",
          "noMultipleSpacesInRegularExpressionLiterals": "error",
          "noUselessCatch": "error",
          "noUselessTypeConstraint": "error"
        },
        "correctness": {
          "noConstAssign": "error",
          "noConstantCondition": "error",
          "noEmptyCharacterClassInRegex": "error",
          "noEmptyPattern": "error",
          "noGlobalObjectCalls": "error",
          "noInvalidConstructorSuper": "error",
          "noInvalidNewBuiltin": "error",
          "noNonoctalDecimalEscape": "error",
          "noPrecisionLoss": "error",
          "noSelfAssign": "error",
          "noSetterReturn": "error",
          "noSwitchDeclarations": "error",
          "noUndeclaredVariables": "error",
          "noUnreachable": "error",
          "noUnreachableSuper": "error",
          "noUnsafeFinally": "error",
          "noUnsafeOptionalChaining": "error",
          "noUnusedLabels": "error",
          "noUnusedVariables": "error",
          "useIsNan": "error",
          "useValidForDirection": "error",
          "useYield": "error"
        }
      }
    },
    "formatter": {
      "enabled": true,
      "formatWithErrors": false,
      "indentStyle": "space",
      "indentWidth": 2,
      "lineWidth": 88,
      "lineEnding": "lf"
    }
  }